{"is_source_file": false, "format": null, "description": "", "external_files": [], "external_methods": [], "published": [], "classes": [], "methods": [], "calls": [], "search-terms": ["personal-notes-organizer-143adb5e"], "state": 2, "file_id": 33, "knowledge_revision": 63, "git_revision": "68f2d9530e7ed96b754f56b17009a837e00d3b70", "hash": "7713caaa4914a207e75da77c9fe1bab6", "format-version": 4, "code-base-name": "notes_frontend", "filename": "README.md", "revision_history": [{"63": "68f2d9530e7ed96b754f56b17009a837e00d3b70"}]}